amsdal_glue/__about__.py
amsdal_glue/__init__.py
amsdal_glue/executors.py
amsdal_glue/initialize.py
amsdal_glue/interfaces.py
amsdal_glue/planners.py
amsdal_glue/py.typed
amsdal_glue/tasks.py
amsdal_glue/applications/__init__.py
amsdal_glue/applications/cqrs.py
amsdal_glue/applications/lakehouse.py
amsdal_glue/commands/__init__.py
amsdal_glue/commands/planner/__init__.py
amsdal_glue/commands/planner/data_planner.py
amsdal_glue/commands/planner/lock_planner.py
amsdal_glue/commands/planner/schema_planner.py
amsdal_glue/commands/planner/transaction_planner.py
amsdal_glue/commands/tasks/__init__.py
amsdal_glue/commands/tasks/data_mutation_tasks.py
amsdal_glue/commands/tasks/lock_tasks.py
amsdal_glue/commands/tasks/schema_mutation_tasks.py
amsdal_glue/commands/tasks/transaction_tasks.py
amsdal_glue/connections/__init__.py
amsdal_glue/connections/connection_manager.py
amsdal_glue/connections/connection_pool.py
amsdal_glue/managers/__init__.py
amsdal_glue/managers/executor_manager.py
amsdal_glue/managers/runtime_manager.py
amsdal_glue/pipelines/__init__.py
amsdal_glue/pipelines/containers.py
amsdal_glue/pipelines/manager.py
amsdal_glue/pipelines/services/__init__.py
amsdal_glue/pipelines/services/router_mixin.py
amsdal_glue/queries/__init__.py
amsdal_glue/queries/polars_operator_constructor.py
amsdal_glue/queries/executors/__init__.py
amsdal_glue/queries/executors/palars_final_query_executor.py
amsdal_glue/queries/planner/__init__.py
amsdal_glue/queries/planner/data_query_planner.py
amsdal_glue/queries/planner/schema_query_planner.py
amsdal_glue/queries/tasks/__init__.py
amsdal_glue/queries/tasks/query_tasks.py
amsdal_glue/queries/tasks/schema_tasks.py
amsdal_glue/services/__init__.py
amsdal_glue/services/data_command.py
amsdal_glue/services/data_query.py
amsdal_glue/services/lock_command.py
amsdal_glue/services/schema_command.py
amsdal_glue/services/schema_query.py
amsdal_glue/services/transaction_command.py
amsdal_glue/task_executors/__init__.py
amsdal_glue-0.1.6.dist-info/METADATA
amsdal_glue-0.1.6.dist-info/WHEEL
amsdal_glue-0.1.6.dist-info/licenses/LICENSE.txt
amsdal_glue-0.1.6.dist-info/licenses/NOTICE.txt
amsdal_glue-0.1.6.dist-info/RECORD
