Metadata-Version: 2.4
Name: amsdal-glue
Version: 0.1.6
Summary: AMSDAL Glue is a Python interface providing high-level abstraction for interacting with multiple databases simultaneously, simplifying the development and maintenance process.
Project-URL: Documentation, https://github.com/amsdal/amsdal-glue?tab=readme-ov-file#amsdal-glue-project
Project-URL: Issues, https://github.com/amsdal/amsdal-glue/issues
Project-URL: Source, https://github.com/amsdal/amsdal-glue/
License:                                  Apache License
License-File: LICENSE.txt
License-File: NOTICE.txt
Classifier: Development Status :: 4 - Beta
Classifier: Programming Language :: Python
Classifier: Programming Language :: Python :: 3.10
Classifier: Programming Language :: Python :: 3.11
Classifier: Programming Language :: Python :: 3.12
Classifier: Programming Language :: Python :: Implementation :: CPython
Classifier: Programming Language :: Python :: Implementation :: PyPy
Requires-Python: >=3.10
Requires-Dist: amsdal-glue-connections>=0.1.0
Requires-Dist: polars>=1.20
Provides-Extra: async-sqlite
Requires-Dist: amsdal-glue-connections[async-sqlite]; extra == 'async-sqlite'
Provides-Extra: csv
Requires-Dist: amsdal-glue-connections[csv]; extra == 'csv'
Provides-Extra: elasticsearch
Requires-Dist: amsdal-glue-connections[elasticsearch]; extra == 'elasticsearch'
Provides-Extra: postgres-binary
Requires-Dist: amsdal-glue-connections[postgres-binary]; extra == 'postgres-binary'
Provides-Extra: postgres-c
Requires-Dist: amsdal-glue-connections[postgres-c]; extra == 'postgres-c'
